CKuhanshuChaxunShouceLongmaGongzuoshi/README.md
CKuhanshuChaxunShouceLongmaGongzuoshi/__init__.py
CKuhanshuChaxunShouceLongmaGongzuoshi/__main__.py
CKuhanshuChaxunShouceLongmaGongzuoshi/file.pdf
CKuhanshuChaxunShouceLongmaGongzuoshi/index.html
c_kuhanshu_chaxun_shouce_longma_gongzuoshi-2024.3.2.0.dist-info/METADATA
c_kuhanshu_chaxun_shouce_longma_gongzuoshi-2024.3.2.0.dist-info/WHEEL
c_kuhanshu_chaxun_shouce_longma_gongzuoshi-2024.3.2.0.dist-info/entry_points.txt
c_kuhanshu_chaxun_shouce_longma_gongzuoshi-2024.3.2.0.dist-info/top_level.txt
c_kuhanshu_chaxun_shouce_longma_gongzuoshi-2024.3.2.0.dist-info/RECORD
